multisport_py/__init__.py
multisport_py/client.py
multisport_py/exceptions.py
multisport_py/py.typed
multisport_py-0.1.3.dist-info/METADATA
multisport_py-0.1.3.dist-info/WHEEL
multisport_py-0.1.3.dist-info/licenses/LICENSE
multisport_py-0.1.3.dist-info/RECORD
