Metadata-Version: 2.4
Name: multisport-py
Version: 0.1.3
Summary: Python client library for interacting with the MultiSport platform.
Project-URL: Homepage, https://github.com/TheUndefined/multisport-py
Author-email: TheUndefined <undefine@aramin.net>
License-Expression: MIT
License-File: LICENSE
Classifier: License :: OSI Approved :: MIT License
Classifier: Operating System :: OS Independent
Classifier: Programming Language :: Python :: 3
Requires-Python: >=3.10
Requires-Dist: httpx
Provides-Extra: dev
Requires-Dist: black; extra == 'dev'
Requires-Dist: mypy; extra == 'dev'
Requires-Dist: pytest; extra == 'dev'
Requires-Dist: pytest-asyncio; extra == 'dev'
Requires-Dist: pytest-cov; extra == 'dev'
Requires-Dist: pytest-httpx; extra == 'dev'
Requires-Dist: python-dotenv; extra == 'dev'
Requires-Dist: ruff; extra == 'dev'
